boardinghouse/__init__.py
boardinghouse/admin.py
boardinghouse/apps.py
boardinghouse/base.py
boardinghouse/context_processors.py
boardinghouse/middleware.py
boardinghouse/models.py
boardinghouse/operations.py
boardinghouse/schema.py
boardinghouse/settings.py
boardinghouse/signals.py
boardinghouse/backends/__init__.py
boardinghouse/backends/postgres/__init__.py
boardinghouse/backends/postgres/base.py
boardinghouse/backends/postgres/schema.py
boardinghouse/contrib/__init__.py
boardinghouse/contrib/demo/__init__.py
boardinghouse/contrib/demo/models.py
boardinghouse/contrib/invite/__init__.py
boardinghouse/contrib/invite/admin.py
boardinghouse/contrib/invite/forms.py
boardinghouse/contrib/invite/models.py
boardinghouse/contrib/invite/urls.py
boardinghouse/contrib/invite/views.py
boardinghouse/contrib/invite/migrations/0001_initial.py
boardinghouse/contrib/invite/migrations/__init__.py
boardinghouse/contrib/template/__init__.py
boardinghouse/contrib/template/admin.py
boardinghouse/contrib/template/models.py
boardinghouse/contrib/template/migrations/0001_initial.py
boardinghouse/contrib/template/migrations/__init__.py
boardinghouse/management/__init__.py
boardinghouse/management/commands/__init__.py
boardinghouse/management/commands/dumpdata.py
boardinghouse/management/commands/flush.py
boardinghouse/management/commands/loaddata.py
boardinghouse/management/commands/migrate.py
boardinghouse/migrations/0001_initial.py
boardinghouse/migrations/0002_patch_admin.py
boardinghouse/migrations/__init__.py
boardinghouse/sql/clone_schema.001.sql
boardinghouse/sql/protect_schema_column.001.sql
boardinghouse/templates/admin/base_site.html
boardinghouse/templates/admin/change_schema.html
boardinghouse/templates/boardinghouse/change_schema.html
boardinghouse/templatetags/__init__.py
boardinghouse/templatetags/boardinghouse.py
django_boardinghouse-0.3.5.dist-info/DESCRIPTION.rst
django_boardinghouse-0.3.5.dist-info/METADATA
django_boardinghouse-0.3.5.dist-info/metadata.json
django_boardinghouse-0.3.5.dist-info/RECORD
django_boardinghouse-0.3.5.dist-info/top_level.txt
django_boardinghouse-0.3.5.dist-info/WHEEL
docs/__init__.py
docs/django_settings.py
tests/__init__.py
tests/admin.py
tests/models.py
tests/settings.py
